<?xml version="1.0" encoding="UTF-8"?>
<Addins>
  <Addin>
    <Name>Cake.Webpack</Name>
    <NuGet Id="Cake.Webpack">
      <Filter>/**/Cake.Webpack.dll</Filter>
      <Filter>/**/Cake.Webpack.xml</Filter>
    </NuGet>
    <Repository>https://github.com/philo/cake-webpack</Repository>
    <Author>Phil Oyston</Author>
    <Description>
      Aliases to assist with running Webpack from Cake build scripts.
    </Description>
    <Categories>Node</Categories>
  </Addin>
  <Addin>
    <Name>Cake.Npm</Name>
    <NuGet Id="Cake.Npm">
      <Filter>/**/Cake.Npm.dll</Filter>
      <Filter>/**/Cake.Npm.xml</Filter>
    </NuGet>
    <Repository>https://github.com/philo/cake-npm</Repository>
    <Author>Phil Oyston</Author>
    <Description>
      A set of aliases for Cake to help with running Npm (Node Package Manager) commands.
    </Description>
    <Categories>Node</Categories>
  </Addin>
  <Addin>
    <Name>Cake.Gulp</Name>
    <NuGet Id="Cake.Gulp">
      <Filter>/**/Cake.Gulp.dll</Filter>
      <Filter>/**/Cake.Gulp.xml</Filter>
    </NuGet>
    <Repository>https://github.com/philo/cake-gulp</Repository>
    <Author>Phil Oyston</Author>
    <Description>
      A set of aliases for Cake to help with running Gulp scripts as part of a build.
    </Description>
    <Categories>Node</Categories>
  </Addin>
  <Addin>
    <Name>Cake.FileHelpers</Name>
    <NuGet Id="Cake.FileHelpers">
      <Filter>/**/Cake.FileHelpers.dll</Filter>
      <Filter>/**/Cake.FileHelpers.xml</Filter>
    </NuGet>
    <Repository>https://github.com/Redth/Cake.FileHelpers</Repository>
    <Author>Jonathan Dick</Author>
    <Description>
      A set of aliases for Cake to help with simple file operations
      such as Reading, Writing and Replacing text.
    </Description>
    <Categories>IO</Categories>
  </Addin>
  <Addin>
    <Name>Cake.Xamarin</Name>
    <NuGet Id="Cake.Xamarin">
      <Filter>/**/Cake.Xamarin.dll</Filter>
      <Filter>/**/Cake.Xamarin.xml</Filter>
    </NuGet>
    <Repository>https://github.com/Redth/Cake.Xamarin</Repository>
    <Author>Jonathan Dick</Author>
    <Description>
      A set of aliases for Cake to help with Xamarin projects.
    </Description>
    <Categories>Mobile</Categories>
  </Addin>
  <Addin>
    <Name>Cake.AliaSql</Name>
    <NuGet Id="Cake.AliaSql" />
    <Repository>https://github.com/RichiCoder1/Cake.AliaSql</Repository>
    <Author>RichieCoder1</Author>
    <Description>
      AliaSql Script Alias for Cake.
    </Description>
    <Categories>Database</Categories>
  </Addin>
  <Addin>
    <Name>Cake.AWS.ElasticLoadBalancing</Name>
    <NuGet Id="Cake.AWS.ElasticLoadBalancing" />
    <Repository>https://github.com/SharpeRAD/Cake.AWS.ElasticLoadBalancing</Repository>
    <Author>SharpeRAD</Author>
    <Description>AWS ElasticLoadBalancing addin for Cake.</Description>
    <Categories>AWS</Categories>
  </Addin>
  <Addin>
    <Name>Cake.AWS.S3</Name>
    <NuGet Id="Cake.AWS.S3" />
    <Repository>https://github.com/SharpeRAD/Cake.AWS.S3</Repository>
    <Author>SharpeRAD</Author>
    <Description>AWS S3 addin for Cake.</Description>
    <Categories>AWS</Categories>
  </Addin>
  <Addin>
    <Name>Cake.Slack</Name>
    <NuGet Id="Cake.Slack">
      <Filter>Cake.Slack.dll</Filter>
      <Filter>Cake.Slack.xml</Filter>
    </NuGet>
    <Repository>https://github.com/WCOMAB/Cake.Slack</Repository>
    <Author>WCOMAB</Author>
    <Description>Cake Addin that extends Cake with Slack messaging features.</Description>
    <Categories>Communication</Categories>
  </Addin>
  <Addin>
    <Name>Cake.Powershell</Name>
    <NuGet Id="Cake.Powershell" />
    <Repository>https://github.com/SharpeRAD/Cake.Powershell</Repository>
    <Author>SharpeRAD</Author>
    <Description>Cake addin that extends Cake with Powershell command support.</Description>
    <Categories>Powershell</Categories>
  </Addin>
  <Addin>
    <Name>Cake.IIS</Name>
    <NuGet Id="Cake.IIS" />
    <Repository>https://github.com/SharpeRAD/Cake.IIS</Repository>
    <Author>SharpeRAD</Author>
    <Description>Cake addin that extends Cake with IIS support.</Description>
    <Categories>IIS</Categories>
  </Addin>
  <Addin>
    <Name>Cake.WebDeploy</Name>
    <NuGet Id="Cake.WebDeploy" />
    <Repository>https://github.com/SharpeRAD/Cake.WebDeploy</Repository>
    <Author>SharpeRAD</Author>
    <Description>Cake addin that extends Cake with WebDeploy commands for publishing to IIS.</Description>
    <Categories>Deployment;IIS</Categories>
  </Addin>
  <Addin>
    <Name>Cake.Services</Name>
    <NuGet Id="Cake.Services" />
    <Repository>https://github.com/SharpeRAD/Cake.Services</Repository>
    <Author>SharpeRAD</Author>
    <Description>Windows Services addin for Cake.</Description>
    <Categories>Windows</Categories>
  </Addin>
  <Addin>
    <Name>Cake.Unity</Name>
    <Repository>https://github.com/cake-contrib/Cake.Unity</Repository>
    <Author>Patrik Svensson</Author>
    <Description>Unity build support for Cake.</Description>
    <Categories>Unity;Gaming</Categories>
  </Addin>
  <Addin>
    <Name>Cake.MSBuildTask</Name>
    <NuGet Id="Cake.MSBuildTask">
      <Filter>Cake.MSBuildTask.dll</Filter>
      <Filter>Cake.MSBuildTask.xml</Filter>
    </NuGet>
    <Repository>https://github.com/marcosnz/Cake.MSBuildTask</Repository>
    <Author>Mark Walker</Author>
    <Description>Adds ability to run any MSBuild task from a Cake script.</Description>
    <Categories>MSBuild</Categories>
  </Addin>
  <Addin>
    <Name>Cake.XCode</Name>
    <NuGet Id="Cake.XCode">
      <Filter>/**/Cake.XCode.dll</Filter>
      <Filter>/**/Cake.XCode.xml</Filter>
    </NuGet>
    <Repository>https://github.com/Redth/Cake.XCode</Repository>
    <Author>Jonathan Dick</Author>
    <Description>A set of aliases for Cake to help with XCode and CocoaPods.</Description>
    <Categories>XCode</Categories>
  </Addin>
  <Addin>
    <Name>Cake.Kudu</Name>
    <NuGet Id="Cake.Kudu">
      <Filter>Cake.Kudu.dll</Filter>
      <Filter>Cake.Kudu.xml</Filter>
    </NuGet>
    <Repository>https://github.com/WCOMAB/Cake.Kudu</Repository>
    <Author>WCOMAB</Author>
    <Description>Cake addin to help with Kudu deployments.</Description>
    <Categories>Azure;Kudu</Categories>
  </Addin>
  <Addin>
    <Name>Cake.CMake</Name>
    <NuGet Id="Cake.CMake">
      <Filter>/**/Cake.CMake.dll</Filter>
      <Filter>/**/Cake.CMake.xml</Filter>
    </NuGet>
    <Repository>https://github.com/cake-contrib/Cake.CMake</Repository>
    <Author>Patrik Svensson</Author>
    <Description>Addin that extends Cake with CMake support.</Description>
    <Categories>CMake</Categories>
  </Addin>
  <Addin>
    <Name>Cake.Gitter</Name>
    <NuGet Id="Cake.Gitter">
      <Filter>/**/Cake.Gitter.dll</Filter>
      <Filter>/**/Cake.Gitter.xml</Filter>
    </NuGet>
    <Repository>https://github.com/cake-contrib/Cake.Gitter</Repository>
    <Author>Gary Ewan Park</Author>
    <Description>Cake Addin to allow message posting to Gitter Room.</Description>
    <Categories>Communication</Categories>
  </Addin>
  <Addin>
    <Name>Cake.Yaml</Name>
    <NuGet Id="Cake.Yaml">
      <Filter>/**/Cake.Yaml.dll</Filter>
      <Filter>/**/Cake.Yaml.xml</Filter>
    </NuGet>
    <Repository>https://github.com/Redth/Cake.Yaml</Repository>
    <Author>Jonathan Dick</Author>
    <Description>
      A set of aliases to help with YAML Serialization
    </Description>
    <Categories>Serialization</Categories>
  </Addin>
  <Addin>
    <Name>Cake.Json</Name>
    <NuGet Id="Cake.Json">
      <Filter>/**/Cake.Json.dll</Filter>
      <Filter>/**/Cake.Json.xml</Filter>
    </NuGet>
    <Repository>https://github.com/Redth/Cake.Json</Repository>
    <Author>Jonathan Dick</Author>
    <Description>
      A set of aliases to help with JSON Serialization
    </Description>
    <Categories>Serialization</Categories>
  </Addin>
  <Addin>
    <Name>Cake.ReSharperReports</Name>
    <NuGet Id="Cake.ReSharperReports">
      <Filter>/**/Cake.ReSharperReports.dll</Filter>
      <Filter>/**/Cake.ReSharperReports.xml</Filter>
    </NuGet>
    <Repository>https://github.com/cake-contrib/Cake.ReSharperReports</Repository>
    <Author>Gary Ewan Park</Author>
    <Description>Cake AddIn that extends Cake with ability to transform ReSharper Reports into human readable format.</Description>
    <Categories>Reports</Categories>
  </Addin>
  <Addin>
    <Name>Cake.AppVeyor</Name>
    <NuGet Id="Cake.AppVeyor">
      <Filter>/**/Cake.AppVeyor.dll</Filter>
      <Filter>/**/Cake.AppVeyor.xml</Filter>
    </NuGet>
    <Repository>https://github.com/Redth/Cake.AppVeyor</Repository>
    <Author>Jonathan Dick</Author>
    <Description>A set of aliases for Cake to access the AppVeyor REST API's</Description>
    <Categories>AppVeyor</Categories>
  </Addin>
  <Addin>
    <Name>Cake.HockeyApp</Name>
    <NuGet Id="Cake.HockeyApp">
      <Filter>/**/Cake.HockeyApp.dll</Filter>
      <Filter>/**/Cake.HockeyApp.xml</Filter>
    </NuGet>
    <Repository>https://github.com/cake-contrib/Cake.HockeyApp</Repository>
    <Author>Paul Reichelt</Author>
    <Description>Cake AddIn that allows you to deploy your app package to HockeyApp.</Description>
    <Categories>Deployment</Categories>
  </Addin>
  <Addin>
    <Name>Cake.VsCode</Name>
    <NuGet Id="Cake.VsCode">
      <Filter>/**/Cake.VsCode.dll</Filter>
      <Filter>/**/Cake.VsCode.xml</Filter>
    </NuGet>
    <Repository>https://github.com/cake-contrib/Cake.VsCode</Repository>
    <Author>Gary Ewan Park</Author>
    <Description>Cake AddIn that extends Cake with ability to execute the vsce command line utility.</Description>
    <Categories>Deployment</Categories>
  </Addin>
  <Addin>
    <Name>Cake.Git</Name>
    <NuGet Id="Cake.Git">
      <Filter>/**/Cake.Git.dll</Filter>
      <Filter>/**/Cake.Git.xml</Filter>
    </NuGet>
    <Repository>https://github.com/WCOMAB/Cake_Git</Repository>
    <Author>WCOM AB</Author>
    <Description>Cake AddIn that extends Cake with Git aliases using LibGit2 and LibGit2Sharp.</Description>
    <Categories>Git</Categories>
  </Addin>
  <Addin>
    <Name>Cake.DocFx</Name>
    <NuGet Id="Cake.DocFx">
      <Filter>/**/Cake.DocFx.dll</Filter>
      <Filter>/**/Cake.DocFx.xml</Filter>
    </NuGet>
    <Repository>https://github.com/cake-contrib/Cake.DocFx</Repository>
    <Author>Paul Reichelt</Author>
    <Description>Cake AddIn that generates documentation for .Net API reference and markdown files using DocFx.</Description>
    <Categories>Documentation</Categories>
  </Addin>
  <Addin>
    <Name>Cake.Wyam</Name>
    <NuGet Id="Cake.Wyam" Version="0.12.2-beta4">
      <Filter>/**/Cake.Wyam.dll</Filter>
      <Filter>/**/Cake.Wyam.xml</Filter>
    </NuGet>
    <Repository>https://github.com/Wyamio/Wyam</Repository>
    <Author>Dave Glick, Gary Ewan Park</Author>
    <Description>An alias that generates static sites and other content using Wyam.</Description>
    <Categories>Documentation;Static Site Generation</Categories>
  </Addin>
  <Addin>
    <Name>Cake.AutoRest</Name>
    <NuGet Id="Cake.AutoRest">
      <Filter>/**/Cake.AutoRest.dll</Filter>
      <Filter>/**/Cake.AutoRest.xml</Filter>
    </NuGet>
    <Repository>https://github.com/agc93/Cake.AutoRest</Repository>
    <Author>Alistair Chapman</Author>
    <Description>Cake addin for generating client code from compatible API definitions (including Swagger).</Description>
    <Categories>Azure;Swagger</Categories>
  </Addin>
  <Addin>
    <Name>Cake.Vagrant</Name>
    <NuGet Id="Cake.Vagrant">
      <Filter>/**/Cake.Vagrant.dll</Filter>
      <Filter>/**/Cake.Vagrant.xml</Filter>
    </NuGet>
    <Repository>https://github.com/cake-contrib/Cake.Vagrant</Repository>
    <Author>Alistair Chapman</Author>
    <Description>Cake addin for creating and managing Vagrant virtual machines</Description>
    <Categories>Vagrant</Categories>
  </Addin>
  <Addin>
    <Name>Cake.Squirrel</Name>
    <NuGet Id="Cake.Squirrel">
      <Filter>/**/Cake.Squirrel.dll</Filter>
      <Filter>/**/Cake.Squirrel.xml</Filter>
    </NuGet>
    <Repository>https://github.com/phillipsj/Cake.Squirrel</Repository>
    <Author>Jamie Phillips</Author>
    <Description>Cake addin for Squirrel.Windows</Description>
    <Categories>Squirrel;Deployment</Categories>
  </Addin>
  <Addin>
    <Name>Cake.XdtTransform</Name>
    <NuGet Id="Cake.XdtTransform">
      <Filter>/**/Cake.XdtTransform.dll</Filter>
      <Filter>/**/Cake.XdtTransform.xml</Filter>
    </NuGet>
    <Repository>https://github.com/phillipsj/Cake.XdtTransform</Repository>
    <Author>Jamie Phillips</Author>
    <Description>Cake addin for performing XDT Transformations</Description>
    <Categories>Serialization;Deployment</Categories>
  </Addin>
  <Addin>
    <Name>Cake.EnvXmlTransform</Name>
    <NuGet Id="Cake.EnvXmlTransform" />
    <Repository>https://github.com/nengberg/cake-envxmltransform</Repository>
    <Author>Niklas Engberg</Author>
    <Description>Cake addin that enables you to transform configuration files based on the environment or machine you're deploying to.</Description>
    <Categories>Deployment</Categories>
  </Addin>
  <Addin>
    <Name>Cake.AzureStorage</Name>
    <NuGet Id="Cake.AzureStorage">
      <Filter>/**/Cake.AzureStorage.dll</Filter>
      <Filter>/**/Cake.AzureStorage.xml</Filter>
    </NuGet>
    <Repository>https://github.com/RadioSystems/Cake.AzureStorage</Repository>
    <Author>Radio Systems Corporation</Author>
    <Description>Cake addin for Azure Storage</Description>
    <Categories>Azure;Deployment</Categories>
  </Addin>
  <Addin>
    <Name>Magic Chunks</Name>
    <NuGet Id="MagicChunks">
      <Filter>/**/MagicChunks.dll</Filter>
      <Filter>/**/MagicChunks.Cake.dll</Filter>
    </NuGet>
    <Repository>https://github.com/sergeyzwezdin/magic-chunks</Repository>
    <Author>Sergey Zwezdin</Author>
    <Description>Easy to use tool to config transformations for JSON, XML and YAML.</Description>
    <Categories>Serialization;IO;Deployment;Configuration</Categories>
  </Addin>
  <Addin>
    <Name>Cake.NSwag</Name>
    <NuGet Id="Cake.NSwag">
      <Filter>/**/Cake.NSwag.dll</Filter>
      <Filter>/**/Cake.NSwag.xml</Filter>
    </NuGet>
    <Repository>https://github.com/agc93/Cake.NSwag</Repository>
    <Author>Alistair Chapman</Author>
    <Description>Cake addin for compiling client code and API definitions (including Swagger) using the NSwag toolchain</Description>
    <Categories>Swagger</Categories>
  </Addin>
  <Addin>
    <Name>Cake.Plist</Name>
    <NuGet Id="Cake.Plist">
      <Filter>/**/Cake.Plist.dll</Filter>
      <Filter>/**/Cake.Plist.xml</Filter>
    </NuGet>
    <Repository>https://github.com/cake-contrib/Cake.Plist</Repository>
    <Author>Paul Reichelt</Author>
    <Description>Cake addin for deserializing, modifying and serializing Apple OSX/iOS xml plists directly from .NET source code.</Description>
    <Categories>Mobile</Categories>
  </Addin>
  <Addin>
    <Name>Cake.AndroidAppManifest</Name>
    <NuGet Id="Cake.AndroidAppManifest">
      <Filter>/**/Cake.AndroidAppManifest.dll</Filter>
      <Filter>/**/Cake.AndroidAppManifest.xml</Filter>
    </NuGet>
    <Repository>https://github.com/ghuntley/Cake.AndroidAppManifest</Repository>
    <Author>Geoffrey Huntley</Author>
    <Description>Cake Build addin for [de]serializing and updating an Android AppManifest.xml.</Description>
    <Categories>Mobile</Categories>
  </Addin>
  <Addin>
    <Name>Cake.Twitter</Name>
    <NuGet Id="Cake.Twitter">
      <Filter>/**/Cake.Twitter.dll</Filter>
      <Filter>/**/Cake.Twitter.xml</Filter>
    </NuGet>
    <Repository>https://github.com/cake-contrib/Cake.Twitter</Repository>
    <Author>Gary Ewan Park</Author>
    <Description>Cake Build addin for tweeting to Twitter.</Description>
    <Categories>Communication;Social Media</Categories>
  </Addin>
  <Addin>
    <Name>Cake.Genymotion</Name>
    <NuGet Id="Cake.Genymotion">
      <Filter>/**/Cake.Genymotion.dll</Filter>
      <Filter>/**/Cake.Genymotion.xml</Filter>
    </NuGet>
    <Repository>https://github.com/ghuntley/Cake.Genymotion</Repository>
    <Author>Geoffrey Huntley</Author>
    <Description>Cake Build addin managing Genymotion (Android) simulators.</Description>
    <Categories>Mobile</Categories>
  </Addin>
  <Addin>
    <Name>Cake.AppleSimulator</Name>
    <NuGet Id="Cake.AppleSimulator">
      <Filter>/**/Cake.AppleSimulator.dll</Filter>
      <Filter>/**/Cake.AppleSimulator.xml</Filter>
    </NuGet>
    <Repository>https://github.com/ghuntley/Cake.AppleSimulator</Repository>
    <Author>Geoffrey Huntley</Author>
    <Description>Cake Build addin for managing (simctl) Apple iOS/watchOS/TV simulators.</Description>
    <Categories>Mobile</Categories>
  </Addin>
  <Addin>
    <Name>Cake.Raygun</Name>
    <NuGet Id="Cake.Raygun">
      <Filter>/**/Cake.Raygun.dll</Filter>
      <Filter>/**/Cake.Raygun.xml</Filter>
    </NuGet>
    <Repository>https://github.com/ghuntley/Cake.Raygun</Repository>
    <Author>Geoffrey Huntley</Author>
    <Description>Cake Build addin for uploading Xamarin.iOS / Objective-C debug symbols (dSYM) to Raygun.io.</Description>
    <Categories>Mobile</Categories>
  </Addin>
  <Addin>
    <Name>Cake.Tfx</Name>
    <NuGet Id="Cake.Tfx">
      <Filter>/**/Cake.Tfx.dll</Filter>
      <Filter>/**/Cake.Tfx.xml</Filter>
    </NuGet>
    <Repository>https://github.com/cake-contrib/Cake.Tfx</Repository>
    <Author>Gary Ewan Park</Author>
    <Description>Cake Build addin for using tfx cli.</Description>
    <Categories>VSTS;TFS;Deployment</Categories>
  </Addin>
  <Addin>
    <Name>Cake.Gem</Name>
    <NuGet Id="Cake.Gem">
      <Filter>/**/Cake.Gem.dll</Filter>
      <Filter>/**/Cake.Gem.xml</Filter>
    </NuGet>
    <Repository>https://github.com/cake-contrib/Cake.Gem</Repository>
    <Author>Gary Ewan Park</Author>
    <Description>Cake Build addin for using gem cli.</Description>
    <Categories>RubyGems;Deployment</Categories>
  </Addin>
  <Addin>
    <Name>Cake.Coveralls</Name>
    <NuGet Id="Cake.Coveralls">
      <Filter>/**/Cake.Coveralls.dll</Filter>
      <Filter>/**/Cake.Coveralls.xml</Filter>
    </NuGet>
    <Repository>https://github.com/cake-contrib/Cake.Coveralls</Repository>
    <Author>Gary Ewan Park</Author>
    <Description>Cake Build addin for publishing code coverage results to coveralls.io.</Description>
    <Categories>Code Coverage;Testing</Categories>
  </Addin>
  <Addin>
    <Name>Cake.SemVer</Name>
    <NuGet Id="Cake.SemVer">
      <Filter>/**/Cake.SemVer.dll</Filter>
      <Filter>/**/Cake.SemVer.xml</Filter>
    </NuGet>
    <Repository>https://github.com/Redth/Cake.SemVer</Repository>
    <Author>Jonathan Dick</Author>
    <Description>Cake build aliases and classes for Semantic Versioning.</Description>
    <Categories>Versioning</Categories>
  </Addin>
  <Addin>
    <Name>Cake.ExtendedNuGet</Name>
    <NuGet Id="Cake.ExtendedNuGet">
      <Filter>/**/Cake.ExtendedNuGet.dll</Filter>
      <Filter>/**/Cake.ExtendedNuGet.xml</Filter>
    </NuGet>
    <Repository>https://github.com/Redth/Cake.ExtendedNuGet</Repository>
    <Author>Jonathan Dick</Author>
    <Description>Cake build aliases and classes additional NuGet functionality.</Description>
    <Categories>NuGet</Categories>
  </Addin>
  <Addin>
    <Name>Cake.Figlet</Name>
    <NuGet Id="Cake.Figlet">
      <Filter>/**/Cake.Figlet.dll</Filter>
      <Filter>/**/Cake.Figlet.xml</Filter>
    </NuGet>
    <Repository>https://github.com/enkafan/Cake.Figlet</Repository>
    <Author>Phil Scott</Author>
    <Description>Cake build aliases and classes for adding ASCII art to your build script output.</Description>
    <Categories>Misc</Categories>
  </Addin>
  <Addin>
    <Name>Cake.SqlServer</Name>
    <NuGet Id="Cake.SqlServer">
      <Filter>/**/Cake.SqlServer.dll</Filter>
      <Filter>/**/Cake.SqlServer.xml</Filter>
    </NuGet>
    <Repository>https://github.com/AMVSoftware/Cake.SqlServer</Repository>
    <Author>Max Vasilyev</Author>
    <Description>Cake build aliases for manipulating SQL Server databases and executing inline SQL and script files.</Description>
    <Categories>SqlServer</Categories>
  </Addin>
  <Addin>
    <Name>Cake.HipChat</Name>
    <NuGet Id="Cake.HipChat">
      <Filter>/**/Cake.HipChat.dll</Filter>
      <Filter>/**/Cake.HipChat.xml</Filter>
    </NuGet>
    <Repository>https://github.com/cake-contrib/Cake.HipChat</Repository>
    <Author>Alan Low</Author>
    <Description>Cake Addin to allow message posting to HipChat.</Description>
    <Categories>Communication</Categories>
  </Addin>
  <Addin>
    <Name>Cake.DoInDirectory</Name>
    <NuGet Id="Cake.DoInDirectory">
      <Filter>/**/Cake.DoInDirectory.dll</Filter>
      <Filter>/**/Cake.DoInDirectory.XML</Filter>
    </NuGet>
    <Repository>https://github.com/pitermarx/Cake.DoInDirectory</Repository>
    <Author>pitermarx</Author>
    <Description>Cake Addin to allow the temporary change of the working directory.</Description>
    <Categories>IO</Categories>
  </Addin>
  <Addin>
    <Name>Cake.SemVer.FromAssembly</Name>
    <NuGet Id="Cake.SemVer.FromAssembly">
      <Filter>/**/Cake.SemVer.FromAssembly.dll</Filter>
      <Filter>/**/Cake.SemVer.FromAssembly.XML</Filter>
    </NuGet>
    <Repository>https://github.com/wallymathieu/Cake.SemVer.FromAssembly</Repository>
    <Author>Oskar Gewalli</Author>
    <Description>Cake Addin to help get version from assembly differences.</Description>
    <Categories>Versioning</Categories>
  </Addin>
</Addins>
